pyryver/__init__.py
pyryver/cache_storage.py
pyryver/doc.py
pyryver/objects.py
pyryver/ryver.py
pyryver/ryver_ws.py
pyryver/util.py
pyryver/version.py
pyryver/ws_data.py
pyryver-0.4.0.post1.dist-info/LICENSE
pyryver-0.4.0.post1.dist-info/METADATA
pyryver-0.4.0.post1.dist-info/WHEEL
pyryver-0.4.0.post1.dist-info/top_level.txt
pyryver-0.4.0.post1.dist-info/RECORD
