Metadata-Version: 2.1
Name: pyryver
Version: 0.4.0.post1
Summary: An unofficial async Python library for Ryver.
Home-page: https://github.com/tylertian123/pyryver
Author: Tyler Tian, Matthew Mirvish
Author-email: tylertian123@gmail.com, matthew@mm12.xyz
Keywords: ryver
Classifier: Programming Language :: Python :: 3
Classifier: License :: OSI Approved :: MIT License
Classifier: Operating System :: OS Independent
Classifier: Development Status :: 3 - Alpha
Requires-Python: >=3.6
License-File: LICENSE
Requires-Dist: aiohttp
